engagevoice/__init__.py
engagevoice/sdk_wrapper.py
engagevoice_sdk_wrapper-0.5.8.dev0.dist-info/METADATA
engagevoice_sdk_wrapper-0.5.8.dev0.dist-info/WHEEL
engagevoice_sdk_wrapper-0.5.8.dev0.dist-info/entry_points.txt
engagevoice_sdk_wrapper-0.5.8.dev0.dist-info/top_level.txt
engagevoice_sdk_wrapper-0.5.8.dev0.dist-info/zip-safe
engagevoice_sdk_wrapper-0.5.8.dev0.dist-info/RECORD
