Metadata-Version: 2.1
Name: engagevoice-sdk-wrapper
Version: 0.5.8.dev0
Summary: RingCentral Engage Voice SDK Wrapper for Python
Home-page: http://engage.ringcentral.com
Author: Phong Vu
Author-email: phong.vu@ringcentral.com
License: UNKNOWN
Keywords: RingCentral,Engage Voice,Contact Center
Platform: UNKNOWN
Requires-Dist: requests
